py2emap/__init__.py
py2emap/__main__.py
py2emap/py2emap.py
py2emap-0.1.0.dist-info/LICENSE
py2emap-0.1.0.dist-info/WHEEL
py2emap-0.1.0.dist-info/METADATA
py2emap-0.1.0.dist-info/RECORD
