Metadata-Version: 2.1
Name: py2emap
Version: 0.1.0
Summary: Convert Python objects to Emap which is friendly data exchange format for Neos VR
Home-page: https://github.com/pluser/py2emap
License: MIT
Author: Nemnomi
Author-email: dev@nemnomi.net
Requires-Python: >=3.6,<4.0
Classifier: License :: OSI Approved :: MIT License
Classifier: Programming Language :: Python :: 3
Classifier: Programming Language :: Python :: 3.10
Classifier: Programming Language :: Python :: 3.6
Classifier: Programming Language :: Python :: 3.7
Classifier: Programming Language :: Python :: 3.8
Classifier: Programming Language :: Python :: 3.9
Project-URL: Repository, https://github.com/pluser/py2emap
